pyttsx3/__init__.py
pyttsx3/driver.py
pyttsx3/engine.py
pyttsx3/voice.py
pyttsx3/drivers/__init__.py
pyttsx3/drivers/_espeak.py
pyttsx3/drivers/dummy.py
pyttsx3/drivers/espeak.py
pyttsx3/drivers/nsss.py
pyttsx3/drivers/sapi5.py
py3_tts-3.4.0.dist-info/LICENSE
py3_tts-3.4.0.dist-info/METADATA
py3_tts-3.4.0.dist-info/WHEEL
py3_tts-3.4.0.dist-info/top_level.txt
py3_tts-3.4.0.dist-info/RECORD
