Metadata-Version: 2.1
Name: py3-tts
Version: 3.4.0
Summary: Text to Speech (TTS) library for Python 3. Works without internet connection or delay. Supports multiple TTS engines, including Sapi5, nsss, and espeak.
Author-email: Vignesh Sivanandha Rao <svignesh1793@gmail.com>
License: Mozilla Public License Version 2.0
Project-URL: Homepage, https://github.com/thevickypedia/py3-tts
Project-URL: Source, https://github.com/thevickypedia/py3-tts
Project-URL: Docs, https://py3-tts.vigneshrao.com
Keywords: pyttsx,ivona,pyttsx for python3,TTS for python3,py3-tts,text to speech for python,tts,text to speech,speech,speech synthesis,offline text to speech,offline tts,gtts
Classifier: Intended Audience :: End Users/Desktop
Classifier: Intended Audience :: Developers
Classifier: Intended Audience :: Information Technology
Classifier: Intended Audience :: System Administrators
Classifier: Operating System :: MacOS :: MacOS X
Classifier: Operating System :: Microsoft :: Windows
Classifier: Operating System :: POSIX
Classifier: License :: OSI Approved :: Mozilla Public License 2.0 (MPL 2.0)
Classifier: Programming Language :: Python :: 3
Classifier: Programming Language :: Python :: 3.5
Classifier: Programming Language :: Python :: 3.6
Classifier: Programming Language :: Python :: 3.7
Requires-Python: >=3
License-File: LICENSE
Requires-Dist: six
Requires-Dist: pyobjc >=2.4 ; platform_system == "Darwin"
Requires-Dist: comtypes ; platform_system == "Windows"
Requires-Dist: pypiwin32 ; platform_system == "Windows"
Requires-Dist: pywin32 ; platform_system == "Windows"
